setup.py
ariastro/__init__.py
ariastro/filegalfit.py
ariastro/library.py
ariastro/visgalfit.py
ariastro.egg-info/PKG-INFO
ariastro.egg-info/SOURCES.txt
ariastro.egg-info/dependency_links.txt
ariastro.egg-info/requires.txt
ariastro.egg-info/top_level.txt
ariastro/scripts/RGBImage.py
ariastro/scripts/correct-image.py
ariastro/scripts/create-output-table.py
ariastro/scripts/create-output-table_bd.py
ariastro/scripts/create-output-table_chi2.py
ariastro/scripts/dump-header.py
ariastro/scripts/galfit-fits-to-png.py
ariastro/scripts/plot-colour.py
ariastro/scripts/plot-comp.py
ariastro/scripts/process-all-bd-fits.py
ariastro/scripts/process-all-exp-fits.py
ariastro/scripts/process-all-fits.py
ariastro/scripts/test-galfit-to-png.py
ariastro/scripts/test-load-jma-gri.py