Metadata-Version: 1.0
Name: ariastro
Version: 0.18.2.28.1
Summary: Ari Astro tools
Home-page: UNKNOWN
Author: UNKNOWN
Author-email: UNKNOWN
License: GNU GPLv3
Platform: any
